<?xml version='1.0' encoding='UTF-8'?>
<!-- Created by LittleOgress-->
<InnerSpaceSettings>
	<Setting Name="Bodyguard XI (Expert)">1</Setting>
	<Setting Name="Lightning Fists X (Expert)">1</Setting>
	<Setting Name="Pummel XI (Expert)">1</Setting>
	<Setting Name="Slurred Insult XII (Expert)">1</Setting>
	<Setting Name="Uppercut IX (Expert)">1</Setting>
	<Setting Name="Devastation Fist IX (Expert)">1</Setting>
	<Setting Name="Meteor Fist XI (Expert)">1</Setting>
	<Setting Name="One Hundred Hand Punch X (Expert)">1</Setting>
	<Setting Name="Roundhouse XI (Expert)">1</Setting>
	<Setting Name="Sonic Punch VII (Expert)">1</Setting>
	<Setting Name="Sucker Punch IX (Expert)">1</Setting>
	<Setting Name="Abuse XI (Expert)">1</Setting>
	<Setting Name="Beatdown XI (Expert)">1</Setting>
	<Setting Name="Brutality XI (Expert)">1</Setting>
	<Setting Name="Ignore Pain VII (Expert)">1</Setting>
	<Setting Name="Manhandle X (Expert)">1</Setting>
	<Setting Name="Smoldering Fists XI (Expert)">1</Setting>
	<Setting Name="Blaze Kick XI (Expert)">1</Setting>
	<Setting Name="Bruising Spirit X (Expert)">1</Setting>
	<Setting Name="Intimidate X (Expert)">1</Setting>
	<Setting Name="Knockout Combination VII (Expert)">1</Setting>
	<Setting Name="Merciless Stomp XI (Expert)">1</Setting>
	<Setting Name="Rock Skin IX (Expert)">1</Setting>
	<Setting Name="Bob and Weave XI (Expert)">1</Setting>
	<Setting Name="Bulwark of Order II (Expert)">1</Setting>
	<Setting Name="Divide and Conquer VI (Expert)">1</Setting>
	<Setting Name="Eye Gouge X (Expert)">1</Setting>
	<Setting Name="Hadooken II (Expert)">1</Setting>
	<Setting Name="Indomitable Will XI (Expert)">1</Setting>
	<Setting Name="Reactive Shell II (Expert)">1</Setting>
	<Setting Name="Savage Assault VIII (Expert)">1</Setting>
	<Setting Name="Shoulder Charge XI (Expert)">1</Setting>
	<Setting Name="Shrug Off VI (Expert)">1</Setting>
</InnerSpaceSettings>


<!--
Room for notes...
-->