<?xml version='1.0' encoding='UTF-8'?>
<!-- Generated by LavishSettings v2 -->
<InnerSpaceSettings>
<Setting Name="Hizite Cloth Bracer of Stratagem">1</Setting>
<Setting Name="Hizite Cloth Gauntlets of Stratagem">1</Setting>
<Setting Name="Hizite Cloth Hood of Stratagem">1</Setting>
<Setting Name="Hizite Cloth Robe of Stratagem">1</Setting>
<Setting Name="Hizite Cloth Boots of Stratagem">1</Setting>
<Setting Name="Hizite Cloth Greaves of Stratagem">1</Setting>
<Setting Name="Hizite Cloth Pauldrons of Stratagem">1</Setting>
</InnerSpaceSettings>

