<?xml version='1.0' encoding='UTF-8'?>
<!-- Created by LittleOgress-->
<InnerSpaceSettings>
	<Setting Name="Brainshock XII (Expert)">1</Setting>
	<Setting Name="Enraging Demeanor IV (Expert)">1</Setting>
	<Setting Name="Hemorrhage XIII (Expert)">1</Setting>
	<Setting Name="Mana Cloak VIII (Expert)">1</Setting>
	<Setting Name="Silence X (Expert)">1</Setting>
	<Setting Name="Stupefy VIII (Expert)">1</Setting>
	<Setting Name="Amnesia V (Expert)">1</Setting>
	<Setting Name="Breeze X (Expert)">1</Setting>
	<Setting Name="Cannibalize Thoughts IX (Expert)">1</Setting>
	<Setting Name="Charm XII (Expert)">1</Setting>
	<Setting Name="Forced Hesitation IX (Expert)">1</Setting>
	<Setting Name="Mind's Eye VIII (Expert)">1</Setting>
	<Setting Name="Obliterated Psyche X (Expert)">1</Setting>
	<Setting Name="Peaceful Link IX (Expert)">1</Setting>
	<Setting Name="Power of Mind XI (Expert)">1</Setting>
	<Setting Name="Simple Minds XI (Expert)">1</Setting>
	<Setting Name="Velocity V (Expert)">1</Setting>
	<Setting Name="Ego Shock XI (Expert)">1</Setting>
	<Setting Name="Hostage X (Expert)">1</Setting>
	<Setting Name="Mesmerize X (Expert)">1</Setting>
	<Setting Name="Pure Awe VIII (Expert)">1</Setting>
	<Setting Name="Spell Curse IX (Expert)">1</Setting>
	<Setting Name="Asylum XI (Expert)">1</Setting>
	<Setting Name="Aura of Power II (Expert)">1</Setting>
	<Setting Name="Destructive Mind X (Expert)">1</Setting>
	<Setting Name="Lethal Focus II (Expert)">1</Setting>
	<Setting Name="Medusa Gaze XII (Expert)">1</Setting>
	<Setting Name="Puppetmaster VI (Expert)">1</Setting>
	<Setting Name="Shift Mana XI (Expert)">1</Setting>
	<Setting Name="Shock Wave VIII (Expert)">1</Setting>
	<Setting Name="Signet of Intellect XI (Expert)">1</Setting>
</InnerSpaceSettings>


<!--
Room for notes...
-->